LICENSE.txt
README.md
setup.cfg
setup.py
dist/pypayments-0.2.2.tar.gz
dist/pypayments-0.2.3.tar.gz
docs/README.rst
docs/index.rst
pypayments/__init__.py
pypayments/cancel_payment.py
pypayments/config.py
pypayments/request_payment.py
pypayments/request_refund.py
pypayments.egg-info/PKG-INFO
pypayments.egg-info/SOURCES.txt
pypayments.egg-info/dependency_links.txt
pypayments.egg-info/top_level.txt