Metadata-Version: 1.0
Name: pypayments
Version: 0.2.5
Summary: Unofficial library for make payments in Python
Home-page: https://github.com/hubtec/pypayments
Author: Daniel Guilhermino
Author-email: daniel@hubtec.com.br
License: MIT
Keywords: ebanx,payments,gateway
Platform: UNKNOWN
